plugins/GroupInsight/__init__.py
plugins/GroupInsight/commands.py
plugins/GroupInsight/database.py
plugins/GroupInsight/message_handler.py
plugins/GroupInsight/models.py
plugins/GroupInsight/scheduler_tasks.py
plugins/GroupInsight/setup.py
hkker-0.1.0.dist-info/METADATA
hkker-0.1.0.dist-info/WHEEL
hkker-0.1.0.dist-info/top_level.txt
hkker-0.1.0.dist-info/RECORD
