Metadata-Version: 2.2
Name: hkker
Version: 0.1.0
Summary: hkker
Requires-Python: <4.0,>=3.9
